arrayfunc/__init__.py
arrayfunc/aall.cp314-win_amd64.pyd
arrayfunc/aany.cp314-win_amd64.pyd
arrayfunc/abs_.cp314-win_amd64.pyd
arrayfunc/acos.cp314-win_amd64.pyd
arrayfunc/acosh.cp314-win_amd64.pyd
arrayfunc/add.cp314-win_amd64.pyd
arrayfunc/afilter.cp314-win_amd64.pyd
arrayfunc/amax.cp314-win_amd64.pyd
arrayfunc/amin.cp314-win_amd64.pyd
arrayfunc/and_.cp314-win_amd64.pyd
arrayfunc/arrayguardbands.cp314-win_amd64.pyd
arrayfunc/arraylimits.cp314-win_amd64.pyd
arrayfunc/asin.cp314-win_amd64.pyd
arrayfunc/asinh.cp314-win_amd64.pyd
arrayfunc/asum.cp314-win_amd64.pyd
arrayfunc/atan.cp314-win_amd64.pyd
arrayfunc/atan2.cp314-win_amd64.pyd
arrayfunc/atanh.cp314-win_amd64.pyd
arrayfunc/ceil.cp314-win_amd64.pyd
arrayfunc/compress.cp314-win_amd64.pyd
arrayfunc/convert.cp314-win_amd64.pyd
arrayfunc/copysign.cp314-win_amd64.pyd
arrayfunc/cos.cp314-win_amd64.pyd
arrayfunc/cosh.cp314-win_amd64.pyd
arrayfunc/count.cp314-win_amd64.pyd
arrayfunc/cycle.cp314-win_amd64.pyd
arrayfunc/degrees.cp314-win_amd64.pyd
arrayfunc/dropwhile.cp314-win_amd64.pyd
arrayfunc/eq.cp314-win_amd64.pyd
arrayfunc/erf.cp314-win_amd64.pyd
arrayfunc/erfc.cp314-win_amd64.pyd
arrayfunc/exp.cp314-win_amd64.pyd
arrayfunc/expm1.cp314-win_amd64.pyd
arrayfunc/fabs.cp314-win_amd64.pyd
arrayfunc/factorial.cp314-win_amd64.pyd
arrayfunc/findindex.cp314-win_amd64.pyd
arrayfunc/findindices.cp314-win_amd64.pyd
arrayfunc/floor.cp314-win_amd64.pyd
arrayfunc/floordiv.cp314-win_amd64.pyd
arrayfunc/fma.cp314-win_amd64.pyd
arrayfunc/fmod.cp314-win_amd64.pyd
arrayfunc/gamma.cp314-win_amd64.pyd
arrayfunc/ge.cp314-win_amd64.pyd
arrayfunc/gt.cp314-win_amd64.pyd
arrayfunc/hypot.cp314-win_amd64.pyd
arrayfunc/invert.cp314-win_amd64.pyd
arrayfunc/isfinite.cp314-win_amd64.pyd
arrayfunc/isinf.cp314-win_amd64.pyd
arrayfunc/isnan.cp314-win_amd64.pyd
arrayfunc/ldexp.cp314-win_amd64.pyd
arrayfunc/le.cp314-win_amd64.pyd
arrayfunc/lgamma.cp314-win_amd64.pyd
arrayfunc/log.cp314-win_amd64.pyd
arrayfunc/log10.cp314-win_amd64.pyd
arrayfunc-8.5.7.dist-info/licenses/LICENSE
arrayfunc-8.5.7.dist-info/METADATA
arrayfunc-8.5.7.dist-info/WHEEL
arrayfunc-8.5.7.dist-info/top_level.txt
arrayfunc-8.5.7.dist-info/RECORD
